LICENSE
MANIFEST.in
README
setup.py
django_paginator.egg-info/PKG-INFO
django_paginator.egg-info/SOURCES.txt
django_paginator.egg-info/dependency_links.txt
django_paginator.egg-info/requires.txt
django_paginator.egg-info/top_level.txt
paginator/__init__.py
paginator/models.py
paginator/views.py
paginator/templates/pagination-nav.html
paginator/templatetags/__init__.py
paginator/templatetags/paginator.py