Metadata-Version: 1.0
Name: django-paginator
Version: 0.2a3
Summary: A template tag that works with Django's Paginator class
Home-page: https://bitbucket.org/nextscreenlabs/django-paginator
Author: Jason Christa
Author-email: jason@zeitcode.com
License: UNKNOWN
Platform: UNKNOWN
Classifier: Environment :: Web Environment
Classifier: License :: OSI Approved :: BSD License
Classifier: Framework :: Django
Classifier: Programming Language :: Python
